mm_crypto_utils/__init__.py
mm_crypto_utils/account.py
mm_crypto_utils/calcs.py
mm_crypto_utils/config_validators.py
mm_crypto_utils/constants.py
mm_crypto_utils/log.py
mm_crypto_utils/node.py
mm_crypto_utils/proxy.py
mm_crypto_utils/py.typed
mm_crypto_utils/retry.py
mm_crypto_utils/utils.py
mm_crypto_utils-0.3.7.dist-info/METADATA
mm_crypto_utils-0.3.7.dist-info/WHEEL
mm_crypto_utils-0.3.7.dist-info/RECORD
