Metadata-Version: 2.4
Name: mm-crypto-utils
Version: 0.3.7
Requires-Python: >=3.12
Requires-Dist: loguru>=0.7.3
Requires-Dist: mm-std>=0.4.12
